[
    {
        "id": 1,
        "nome": "Milena Martins",
        "uf": "Outros",
        "cnae_ocupacao": "Outros",
        "porte": "Mais de 5 a 10 salários mínimos",
        "modalidade": "Empréstimos",
        "submodalidade": "Cheque especial",
        "numero_de_operacoes": 2.0,
        "carteira_a_vencer": 28022.59,
        "a_vencer_ate_90_dias": 24585.48,
        "a_vencer_de_91_ate_360_dias": 850.54,
        "a_vencer_de_361_ate_1080_dias": 2586.57,
        "a_vencer_de_1081_ate_1800_dias": 0.0,
        "a_vencer_de_1801_ate_5400_dias": 0.0,
        "a_vencer_acima_de_5400_dias": 0.0,
        "risk_percent": 34.21,
        "risk_status": "Médio"
    },
    {
        "id": 2,
        "nome": "Bruno Lima",
        "uf": "MG",
        "cnae_ocupacao": "MEI",
        "porte": "Mais de 2 a 3 salários mínimos",
        "modalidade": "Financiamentos",
        "submodalidade": "Crédito pessoal - sem consignação em folha de pagam.",
        "numero_de_operacoes": 5.0,
        "carteira_a_vencer": 41499.19,
        "a_vencer_ate_90_dias": 22091.93,
        "a_vencer_de_91_ate_360_dias": 6395.39,
        "a_vencer_de_361_ate_1080_dias": 13011.87,
        "a_vencer_de_1081_ate_1800_dias": 0.0,
        "a_vencer_de_1801_ate_5400_dias": 0.0,
        "a_vencer_acima_de_5400_dias": 0.0,
        "risk_percent": 47.78,
        "risk_status": "Médio"
    },
    {
        "id": 3,
        "nome": "Bruno Costa",
        "uf": "SP",
        "cnae_ocupacao": "MEI",
        "porte": "Mais de 3 a 5 salários mínimos",
        "modalidade": "Outros créditos",
        "submodalidade": "Outros",
        "numero_de_operacoes": 18.0,
        "carteira_a_vencer": 49139.23,
        "a_vencer_ate_90_dias": 21723.04,
        "a_vencer_de_91_ate_360_dias": 22840.36,
        "a_vencer_de_361_ate_1080_dias": 4575.83,
        "a_vencer_de_1081_ate_1800_dias": 0.0,
        "a_vencer_de_1801_ate_5400_dias": 0.0,
        "a_vencer_acima_de_5400_dias": 0.0,
        "risk_percent": 82.85,
        "risk_status": "Alto"
    },
    {
        "id": 4,
        "nome": "Pedro Almeida",
        "uf": "SP",
        "cnae_ocupacao": "MEI",
        "porte": "Mais de 5 a 10 salários mínimos",
        "modalidade": "Financiamentos imobiliários",
        "submodalidade": "Cheque especial",
        "numero_de_operacoes": 20.0,
        "carteira_a_vencer": 3774.45,
        "a_vencer_ate_90_dias": 973.01,
        "a_vencer_de_91_ate_360_dias": 1584.16,
        "a_vencer_de_361_ate_1080_dias": 1217.28,
        "a_vencer_de_1081_ate_1800_dias": 0.0,
        "a_vencer_de_1801_ate_5400_dias": 0.0,
        "a_vencer_acima_de_5400_dias": 0.0,
        "risk_percent": 71.58,
        "risk_status": "Alto"
    },
    {
        "id": 5,
        "nome": "Rodrigo Silva",
        "uf": "RJ",
        "cnae_ocupacao": "Empregado de empresa privada",
        "porte": "Mais de 1 a 2 salários mínimos",
        "modalidade": "Operações de arrendamento",
        "submodalidade": "Financiamento habitacional - SFH",
        "numero_de_operacoes": 3.0,
        "carteira_a_vencer": 22430.28,
        "a_vencer_ate_90_dias": 15960.96,
        "a_vencer_de_91_ate_360_dias": 5924.66,
        "a_vencer_de_361_ate_1080_dias": 544.66,
        "a_vencer_de_1081_ate_1800_dias": 0.0,
        "a_vencer_de_1801_ate_5400_dias": 0.0,
        "a_vencer_acima_de_5400_dias": 0.0,
        "risk_percent": 47.06,
        "risk_status": "Médio"
    },
    {
        "id": 6,
        "nome": "Bruno Almeida",
        "uf": "PR",
        "cnae_ocupacao": "Servidor ou empregado público",
        "porte": "Mais de 1 a 2 salários mínimos",
        "modalidade": "Financiamentos imobiliários",
        "submodalidade": "Crédito pessoal - sem consignação em folha de pagam.",
        "numero_de_operacoes": 4.0,
        "carteira_a_vencer": 41979.58,
        "a_vencer_ate_90_dias": 35287.9,
        "a_vencer_de_91_ate_360_dias": 2580.76,
        "a_vencer_de_361_ate_1080_dias": 4110.92,
        "a_vencer_de_1081_ate_1800_dias": 0.0,
        "a_vencer_de_1801_ate_5400_dias": 0.0,
        "a_vencer_acima_de_5400_dias": 0.0,
        "risk_percent": 38.33,
        "risk_status": "Médio"
    },
    {
        "id": 7,
        "nome": "Carlos Carvalho",
        "uf": "AC",
        "cnae_ocupacao": "Outros",
        "porte": "Indisponível",
        "modalidade": "Financiamentos imobiliários",
        "submodalidade": "Outros",
        "numero_de_operacoes": 12.0,
        "carteira_a_vencer": 37673.99,
        "a_vencer_ate_90_dias": 5577.33,
        "a_vencer_de_91_ate_360_dias": 8212.07,
        "a_vencer_de_361_ate_1080_dias": 23884.59,
        "a_vencer_de_1081_ate_1800_dias": 0.0,
        "a_vencer_de_1801_ate_5400_dias": 0.0,
        "a_vencer_acima_de_5400_dias": 0.0,
        "risk_percent": 50.05,
        "risk_status": "Médio"
    },
    {
        "id": 8,
        "nome": "Marcos Oliveira",
        "uf": "RJ",
        "cnae_ocupacao": "Empregado de empresa privada",
        "porte": "Mais de 2 a 3 salários mínimos",
        "modalidade": "Financiamentos imobiliários",
        "submodalidade": "Cheque especial",
        "numero_de_operacoes": 6.0,
        "carteira_a_vencer": 48996.3,
        "a_vencer_ate_90_dias": 19901.07,
        "a_vencer_de_91_ate_360_dias": 3969.69,
        "a_vencer_de_361_ate_1080_dias": 25125.54,
        "a_vencer_de_1081_ate_1800_dias": 0.0,
        "a_vencer_de_1801_ate_5400_dias": 0.0,
        "a_vencer_acima_de_5400_dias": 0.0,
        "risk_percent": 46.14,
        "risk_status": "Médio"
    },
    {
        "id": 9,
        "nome": "Rodrigo Lima",
        "uf": "AC",
        "cnae_ocupacao": "Empresário",
        "porte": "Mais de 10 a 20 salários mínimos",
        "modalidade": "Operações de arrendamento",
        "submodalidade": "Aquisição de bens - veículos automotores",
        "numero_de_operacoes": 15.0,
        "carteira_a_vencer": 22659.18,
        "a_vencer_ate_90_dias": 10330.61,
        "a_vencer_de_91_ate_360_dias": 1782.45,
        "a_vencer_de_361_ate_1080_dias": 10546.12,
        "a_vencer_de_1081_ate_1800_dias": 0.0,
        "a_vencer_de_1801_ate_5400_dias": 0.0,
        "a_vencer_acima_de_5400_dias": 0.0,
        "risk_percent": 73.89,
        "risk_status": "Alto"
    },
    {
        "id": 10,
        "nome": "João Oliveira",
        "uf": "MG",
        "cnae_ocupacao": "Servidor ou empregado público",
        "porte": "Sem rendimento",
        "modalidade": "Financiamentos imobiliários",
        "submodalidade": "Cartão de crédito - compra, fatura parcelada ou saque financiado pela instituição financeira emitente do cartão",
        "numero_de_operacoes": 9.0,
        "carteira_a_vencer": 49415.87,
        "a_vencer_ate_90_dias": 13312.89,
        "a_vencer_de_91_ate_360_dias": 18726.42,
        "a_vencer_de_361_ate_1080_dias": 17376.56,
        "a_vencer_de_1081_ate_1800_dias": 0.0,
        "a_vencer_de_1801_ate_5400_dias": 0.0,
        "a_vencer_acima_de_5400_dias": 0.0,
        "risk_percent": 54.1,
        "risk_status": "Médio"
    },
    {
        "id": 11,
        "nome": "Marcos Santos",
        "uf": "Outros",
        "cnae_ocupacao": "MEI",
        "porte": "Mais de 10 a 20 salários mínimos",
        "modalidade": "Financiamentos",
        "submodalidade": "Aquisição de bens - veículos automotores",
        "numero_de_operacoes": 18.0,
        "carteira_a_vencer": 6445.95,
        "a_vencer_ate_90_dias": 3128.58,
        "a_vencer_de_91_ate_360_dias": 2972.68,
        "a_vencer_de_361_ate_1080_dias": 344.69,
        "a_vencer_de_1081_ate_1800_dias": 0.0,
        "a_vencer_de_1801_ate_5400_dias": 0.0,
        "a_vencer_acima_de_5400_dias": 0.0,
        "risk_percent": 81.7,
        "risk_status": "Alto"
    },
    {
        "id": 12,
        "nome": "João Alves",
        "uf": "MG",
        "cnae_ocupacao": "Empregado de empresa privada",
        "porte": "Mais de 10 a 20 salários mínimos",
        "modalidade": "Financiamentos",
        "submodalidade": "Cheque especial",
        "numero_de_operacoes": 1.0,
        "carteira_a_vencer": 30817.9,
        "a_vencer_ate_90_dias": 16607.65,
        "a_vencer_de_91_ate_360_dias": 12469.77,
        "a_vencer_de_361_ate_1080_dias": 1740.48,
        "a_vencer_de_1081_ate_1800_dias": 0.0,
        "a_vencer_de_1801_ate_5400_dias": 0.0,
        "a_vencer_acima_de_5400_dias": 0.0,
        "risk_percent": 34.41,
        "risk_status": "Médio"
    },
    {
        "id": 13,
        "nome": "Amanda Almeida",
        "uf": "Outros",
        "cnae_ocupacao": "Outros",
        "porte": "Até 1 salário mínimo",
        "modalidade": "Financiamentos",
        "submodalidade": "Crédito pessoal - sem consignação em folha de pagam.",
        "numero_de_operacoes": 4.0,
        "carteira_a_vencer": 22926.73,
        "a_vencer_ate_90_dias": 1144.67,
        "a_vencer_de_91_ate_360_dias": 5666.23,
        "a_vencer_de_361_ate_1080_dias": 16115.83,
        "a_vencer_de_1081_ate_1800_dias": 0.0,
        "a_vencer_de_1801_ate_5400_dias": 0.0,
        "a_vencer_acima_de_5400_dias": 0.0,
        "risk_percent": 45.25,
        "risk_status": "Médio"
    },
    {
        "id": 14,
        "nome": "Amanda Ferreira",
        "uf": "SC",
        "cnae_ocupacao": "Servidor ou empregado público",
        "porte": "Até 1 salário mínimo",
        "modalidade": "Financiamentos",
        "submodalidade": "Outros",
        "numero_de_operacoes": 16.0,
        "carteira_a_vencer": 42181.43,
        "a_vencer_ate_90_dias": 25100.15,
        "a_vencer_de_91_ate_360_dias": 3917.54,
        "a_vencer_de_361_ate_1080_dias": 13163.74,
        "a_vencer_de_1081_ate_1800_dias": 0.0,
        "a_vencer_de_1801_ate_5400_dias": 0.0,
        "a_vencer_acima_de_5400_dias": 0.0,
        "risk_percent": 61.14,
        "risk_status": "Médio"
    },
    {
        "id": 15,
        "nome": "Bruno Oliveira",
        "uf": "SC",
        "cnae_ocupacao": "Empresário",
        "porte": "Mais de 3 a 5 salários mínimos",
        "modalidade": "Empréstimos",
        "submodalidade": "Cheque especial",
        "numero_de_operacoes": 3.0,
        "carteira_a_vencer": 40668.88,
        "a_vencer_ate_90_dias": 19189.89,
        "a_vencer_de_91_ate_360_dias": 3574.9,
        "a_vencer_de_361_ate_1080_dias": 17904.09,
        "a_vencer_de_1081_ate_1800_dias": 0.0,
        "a_vencer_de_1801_ate_5400_dias": 0.0,
        "a_vencer_acima_de_5400_dias": 0.0,
        "risk_percent": 40.53,
        "risk_status": "Médio"
    },
    {
        "id": 16,
        "nome": "Rafael Costa",
        "uf": "RJ",
        "cnae_ocupacao": "Servidor ou empregado público",
        "porte": "Mais de 10 a 20 salários mínimos",
        "modalidade": "Financiamentos",
        "submodalidade": "Crédito pessoal - sem consignação em folha de pagam.",
        "numero_de_operacoes": 7.0,
        "carteira_a_vencer": 39575.52,
        "a_vencer_ate_90_dias": 7256.46,
        "a_vencer_de_91_ate_360_dias": 7794.87,
        "a_vencer_de_361_ate_1080_dias": 24524.19,
        "a_vencer_de_1081_ate_1800_dias": 0.0,
        "a_vencer_de_1801_ate_5400_dias": 0.0,
        "a_vencer_acima_de_5400_dias": 0.0,
        "risk_percent": 57.66,
        "risk_status": "Médio"
    },
    {
        "id": 17,
        "nome": "Milena Ferreira",
        "uf": "AC",
        "cnae_ocupacao": "Outros",
        "porte": "Mais de 5 a 10 salários mínimos",
        "modalidade": "Outros créditos",
        "submodalidade": "Outros",
        "numero_de_operacoes": 3.0,
        "carteira_a_vencer": 49685.79,
        "a_vencer_ate_90_dias": 7537.82,
        "a_vencer_de_91_ate_360_dias": 33916.85,
        "a_vencer_de_361_ate_1080_dias": 8231.12,
        "a_vencer_de_1081_ate_1800_dias": 0.0,
        "a_vencer_de_1801_ate_5400_dias": 0.0,
        "a_vencer_acima_de_5400_dias": 0.0,
        "risk_percent": 44.37,
        "risk_status": "Médio"
    },
    {
        "id": 18,
        "nome": "Carlos Souza",
        "uf": "PR",
        "cnae_ocupacao": "Empregado de empresa privada",
        "porte": "Sem rendimento",
        "modalidade": "Financiamentos imobiliários",
        "submodalidade": "Cartão de crédito - compra, fatura parcelada ou saque financiado pela instituição financeira emitente do cartão",
        "numero_de_operacoes": 4.0,
        "carteira_a_vencer": 26969.39,
        "a_vencer_ate_90_dias": 20792.86,
        "a_vencer_de_91_ate_360_dias": 4006.43,
        "a_vencer_de_361_ate_1080_dias": 2170.1,
        "a_vencer_de_1081_ate_1800_dias": 0.0,
        "a_vencer_de_1801_ate_5400_dias": 0.0,
        "a_vencer_acima_de_5400_dias": 0.0,
        "risk_percent": 48.8,
        "risk_status": "Médio"
    },
    {
        "id": 19,
        "nome": "Juliana Oliveira",
        "uf": "Outros",
        "cnae_ocupacao": "Servidor ou empregado público",
        "porte": "Sem rendimento",
        "modalidade": "Operações de arrendamento",
        "submodalidade": "Cheque especial",
        "numero_de_operacoes": 15.0,
        "carteira_a_vencer": 9094.57,
        "a_vencer_ate_90_dias": 4245.77,
        "a_vencer_de_91_ate_360_dias": 890.81,
        "a_vencer_de_361_ate_1080_dias": 3957.99,
        "a_vencer_de_1081_ate_1800_dias": 0.0,
        "a_vencer_de_1801_ate_5400_dias": 0.0,
        "a_vencer_acima_de_5400_dias": 0.0,
        "risk_percent": 75.21,
        "risk_status": "Alto"
    },
    {
        "id": 20,
        "nome": "Lucas Costa",
        "uf": "AC",
        "cnae_ocupacao": "Outros",
        "porte": "Mais de 3 a 5 salários mínimos",
        "modalidade": "Outros créditos",
        "submodalidade": "Financiamento habitacional - SFH",
        "numero_de_operacoes": 9.0,
        "carteira_a_vencer": 48197.92,
        "a_vencer_ate_90_dias": 2579.5,
        "a_vencer_de_91_ate_360_dias": 18935.06,
        "a_vencer_de_361_ate_1080_dias": 26683.36,
        "a_vencer_de_1081_ate_1800_dias": 0.0,
        "a_vencer_de_1801_ate_5400_dias": 0.0,
        "a_vencer_acima_de_5400_dias": 0.0,
        "risk_percent": 56.2,
        "risk_status": "Médio"
    },
    {
        "id": 21,
        "nome": "Bruno Martins",
        "uf": "RS",
        "cnae_ocupacao": "Empresário",
        "porte": "Sem rendimento",
        "modalidade": "Operações de arrendamento",
        "submodalidade": "Outros",
        "numero_de_operacoes": 16.0,
        "carteira_a_vencer": 39420.92,
        "a_vencer_ate_90_dias": 35792.62,
        "a_vencer_de_91_ate_360_dias": 2279.46,
        "a_vencer_de_361_ate_1080_dias": 1348.84,
        "a_vencer_de_1081_ate_1800_dias": 0.0,
        "a_vencer_de_1801_ate_5400_dias": 0.0,
        "a_vencer_acima_de_5400_dias": 0.0,
        "risk_percent": 67.24,
        "risk_status": "Médio"
    },
    {
        "id": 22,
        "nome": "Fernanda Oliveira",
        "uf": "SP",
        "cnae_ocupacao": "MEI",
        "porte": "Mais de 3 a 5 salários mínimos",
        "modalidade": "Operações de arrendamento",
        "submodalidade": "Aquisição de bens - veículos automotores",
        "numero_de_operacoes": 5.0,
        "carteira_a_vencer": 45297.97,
        "a_vencer_ate_90_dias": 3136.24,
        "a_vencer_de_91_ate_360_dias": 32486.82,
        "a_vencer_de_361_ate_1080_dias": 9674.91,
        "a_vencer_de_1081_ate_1800_dias": 0.0,
        "a_vencer_de_1801_ate_5400_dias": 0.0,
        "a_vencer_acima_de_5400_dias": 0.0,
        "risk_percent": 39.35,
        "risk_status": "Médio"
    },
    {
        "id": 23,
        "nome": "João Pereira",
        "uf": "Outros",
        "cnae_ocupacao": "Autônomo",
        "porte": "Mais de 2 a 3 salários mínimos",
        "modalidade": "Outros créditos",
        "submodalidade": "Crédito pessoal - sem consignação em folha de pagam.",
        "numero_de_operacoes": 16.0,
        "carteira_a_vencer": 19738.54,
        "a_vencer_ate_90_dias": 15560.69,
        "a_vencer_de_91_ate_360_dias": 31.33,
        "a_vencer_de_361_ate_1080_dias": 4146.52,
        "a_vencer_de_1081_ate_1800_dias": 0.0,
        "a_vencer_de_1801_ate_5400_dias": 0.0,
        "a_vencer_acima_de_5400_dias": 0.0,
        "risk_percent": 75.07,
        "risk_status": "Alto"
    },
    {
        "id": 24,
        "nome": "Juliana Santos",
        "uf": "Outros",
        "cnae_ocupacao": "Empregado de empresa privada",
        "porte": "Mais de 5 a 10 salários mínimos",
        "modalidade": "Financiamentos imobiliários",
        "submodalidade": "Cartão de crédito - compra, fatura parcelada ou saque financiado pela instituição financeira emitente do cartão",
        "numero_de_operacoes": 11.0,
        "carteira_a_vencer": 33940.74,
        "a_vencer_ate_90_dias": 33867.81,
        "a_vencer_de_91_ate_360_dias": 72.15,
        "a_vencer_de_361_ate_1080_dias": 0.78,
        "a_vencer_de_1081_ate_1800_dias": 0.0,
        "a_vencer_de_1801_ate_5400_dias": 0.0,
        "a_vencer_acima_de_5400_dias": 0.0,
        "risk_percent": 61.6,
        "risk_status": "Médio"
    },
    {
        "id": 25,
        "nome": "Letícia Lima",
        "uf": "Outros",
        "cnae_ocupacao": "Servidor ou empregado público",
        "porte": "Mais de 2 a 3 salários mínimos",
        "modalidade": "Outros créditos",
        "submodalidade": "Crédito pessoal - sem consignação em folha de pagam.",
        "numero_de_operacoes": 5.0,
        "carteira_a_vencer": 18112.09,
        "a_vencer_ate_90_dias": 10492.25,
        "a_vencer_de_91_ate_360_dias": 5322.18,
        "a_vencer_de_361_ate_1080_dias": 2297.66,
        "a_vencer_de_1081_ate_1800_dias": 0.0,
        "a_vencer_de_1801_ate_5400_dias": 0.0,
        "a_vencer_acima_de_5400_dias": 0.0,
        "risk_percent": 55.88,
        "risk_status": "Médio"
    },
    {
        "id": 26,
        "nome": "Bruno Costa",
        "uf": "PR",
        "cnae_ocupacao": "Empregado de empresa privada",
        "porte": "Até 1 salário mínimo",
        "modalidade": "Empréstimos",
        "submodalidade": "Cartão de crédito - compra, fatura parcelada ou saque financiado pela instituição financeira emitente do cartão",
        "numero_de_operacoes": 4.0,
        "carteira_a_vencer": 1939.38,
        "a_vencer_ate_90_dias": 1797.35,
        "a_vencer_de_91_ate_360_dias": 20.96,
        "a_vencer_de_361_ate_1080_dias": 121.07,
        "a_vencer_de_1081_ate_1800_dias": 0.0,
        "a_vencer_de_1801_ate_5400_dias": 0.0,
        "a_vencer_acima_de_5400_dias": 0.0,
        "risk_percent": 65.16,
        "risk_status": "Médio"
    },
    {
        "id": 27,
        "nome": "Pedro Carvalho",
        "uf": "AC",
        "cnae_ocupacao": "Empregado de empresa privada",
        "porte": "Mais de 5 a 10 salários mínimos",
        "modalidade": "Operações de arrendamento",
        "submodalidade": "Cartão de crédito - compra, fatura parcelada ou saque financiado pela instituição financeira emitente do cartão",
        "numero_de_operacoes": 3.0,
        "carteira_a_vencer": 5224.68,
        "a_vencer_ate_90_dias": 350.7,
        "a_vencer_de_91_ate_360_dias": 4472.04,
        "a_vencer_de_361_ate_1080_dias": 401.94,
        "a_vencer_de_1081_ate_1800_dias": 0.0,
        "a_vencer_de_1801_ate_5400_dias": 0.0,
        "a_vencer_acima_de_5400_dias": 0.0,
        "risk_percent": 62.58,
        "risk_status": "Médio"
    },
    {
        "id": 28,
        "nome": "Amanda Alves",
        "uf": "MG",
        "cnae_ocupacao": "Autônomo",
        "porte": "Mais de 5 a 10 salários mínimos",
        "modalidade": "Operações de arrendamento",
        "submodalidade": "Cartão de crédito - compra, fatura parcelada ou saque financiado pela instituição financeira emitente do cartão",
        "numero_de_operacoes": 10.0,
        "carteira_a_vencer": 26560.79,
        "a_vencer_ate_90_dias": 23641.01,
        "a_vencer_de_91_ate_360_dias": 2528.45,
        "a_vencer_de_361_ate_1080_dias": 391.33,
        "a_vencer_de_1081_ate_1800_dias": 0.0,
        "a_vencer_de_1801_ate_5400_dias": 0.0,
        "a_vencer_acima_de_5400_dias": 0.0,
        "risk_percent": 64.27,
        "risk_status": "Médio"
    },
    {
        "id": 29,
        "nome": "Rodrigo Ferreira",
        "uf": "SC",
        "cnae_ocupacao": "Servidor ou empregado público",
        "porte": "Indisponível",
        "modalidade": "Financiamentos imobiliários",
        "submodalidade": "Financiamento habitacional - SFH",
        "numero_de_operacoes": 19.0,
        "carteira_a_vencer": 49307.72,
        "a_vencer_ate_90_dias": 33972.85,
        "a_vencer_de_91_ate_360_dias": 145.61,
        "a_vencer_de_361_ate_1080_dias": 15189.26,
        "a_vencer_de_1081_ate_1800_dias": 0.0,
        "a_vencer_de_1801_ate_5400_dias": 0.0,
        "a_vencer_acima_de_5400_dias": 0.0,
        "risk_percent": 57.8,
        "risk_status": "Médio"
    },
    {
        "id": 30,
        "nome": "Lucas Pereira",
        "uf": "Outros",
        "cnae_ocupacao": "Empregado de empresa privada",
        "porte": "Sem rendimento",
        "modalidade": "Empréstimos",
        "submodalidade": "Outros",
        "numero_de_operacoes": 17.0,
        "carteira_a_vencer": 4978.49,
        "a_vencer_ate_90_dias": 2041.02,
        "a_vencer_de_91_ate_360_dias": 222.21,
        "a_vencer_de_361_ate_1080_dias": 2715.26,
        "a_vencer_de_1081_ate_1800_dias": 0.0,
        "a_vencer_de_1801_ate_5400_dias": 0.0,
        "a_vencer_acima_de_5400_dias": 0.0,
        "risk_percent": 66.73,
        "risk_status": "Médio"
    },
    {
        "id": 31,
        "nome": "Ana Pereira",
        "uf": "PR",
        "cnae_ocupacao": "Empresário",
        "porte": "Até 1 salário mínimo",
        "modalidade": "Financiamentos",
        "submodalidade": "Crédito pessoal - com consignação em folha de pagam.",
        "numero_de_operacoes": 15.0,
        "carteira_a_vencer": 29888.38,
        "a_vencer_ate_90_dias": 27719.11,
        "a_vencer_de_91_ate_360_dias": 314.99,
        "a_vencer_de_361_ate_1080_dias": 1854.28,
        "a_vencer_de_1081_ate_1800_dias": 0.0,
        "a_vencer_de_1801_ate_5400_dias": 0.0,
        "a_vencer_acima_de_5400_dias": 0.0,
        "risk_percent": 67.45,
        "risk_status": "Médio"
    },
    {
        "id": 32,
        "nome": "Juliana Souza",
        "uf": "Outros",
        "cnae_ocupacao": "Empregado de empresa privada",
        "porte": "Mais de 3 a 5 salários mínimos",
        "modalidade": "Outros créditos",
        "submodalidade": "Cartão de crédito - compra, fatura parcelada ou saque financiado pela instituição financeira emitente do cartão",
        "numero_de_operacoes": 2.0,
        "carteira_a_vencer": 14011.01,
        "a_vencer_ate_90_dias": 2233.59,
        "a_vencer_de_91_ate_360_dias": 4748.09,
        "a_vencer_de_361_ate_1080_dias": 7029.33,
        "a_vencer_de_1081_ate_1800_dias": 0.0,
        "a_vencer_de_1801_ate_5400_dias": 0.0,
        "a_vencer_acima_de_5400_dias": 0.0,
        "risk_percent": 42.44,
        "risk_status": "Médio"
    },
    {
        "id": 33,
        "nome": "Carlos Ferreira",
        "uf": "RS",
        "cnae_ocupacao": "Servidor ou empregado público",
        "porte": "Mais de 1 a 2 salários mínimos",
        "modalidade": "Financiamentos imobiliários",
        "submodalidade": "Crédito pessoal - sem consignação em folha de pagam.",
        "numero_de_operacoes": 9.0,
        "carteira_a_vencer": 39326.49,
        "a_vencer_ate_90_dias": 1666.52,
        "a_vencer_de_91_ate_360_dias": 13062.69,
        "a_vencer_de_361_ate_1080_dias": 24597.28,
        "a_vencer_de_1081_ate_1800_dias": 0.0,
        "a_vencer_de_1801_ate_5400_dias": 0.0,
        "a_vencer_acima_de_5400_dias": 0.0,
        "risk_percent": 43.77,
        "risk_status": "Médio"
    },
    {
        "id": 34,
        "nome": "Marcos Lima",
        "uf": "Outros",
        "cnae_ocupacao": "Empregado de empresa privada",
        "porte": "Até 1 salário mínimo",
        "modalidade": "Outros créditos",
        "submodalidade": "Crédito pessoal - sem consignação em folha de pagam.",
        "numero_de_operacoes": 3.0,
        "carteira_a_vencer": 33317.14,
        "a_vencer_ate_90_dias": 1524.28,
        "a_vencer_de_91_ate_360_dias": 19263.03,
        "a_vencer_de_361_ate_1080_dias": 12529.83,
        "a_vencer_de_1081_ate_1800_dias": 0.0,
        "a_vencer_de_1801_ate_5400_dias": 0.0,
        "a_vencer_acima_de_5400_dias": 0.0,
        "risk_percent": 30.03,
        "risk_status": "Médio"
    },
    {
        "id": 35,
        "nome": "Bruno Oliveira",
        "uf": "AC",
        "cnae_ocupacao": "Empregado de empresa privada",
        "porte": "Mais de 2 a 3 salários mínimos",
        "modalidade": "Empréstimos",
        "submodalidade": "Cartão de crédito - compra, fatura parcelada ou saque financiado pela instituição financeira emitente do cartão",
        "numero_de_operacoes": 19.0,
        "carteira_a_vencer": 27461.11,
        "a_vencer_ate_90_dias": 1822.6,
        "a_vencer_de_91_ate_360_dias": 23887.51,
        "a_vencer_de_361_ate_1080_dias": 1751.0,
        "a_vencer_de_1081_ate_1800_dias": 0.0,
        "a_vencer_de_1801_ate_5400_dias": 0.0,
        "a_vencer_acima_de_5400_dias": 0.0,
        "risk_percent": 69.83,
        "risk_status": "Médio"
    },
    {
        "id": 36,
        "nome": "Marcos Oliveira",
        "uf": "SC",
        "cnae_ocupacao": "Empregado de empresa privada",
        "porte": "Mais de 3 a 5 salários mínimos",
        "modalidade": "Empréstimos",
        "submodalidade": "Outros",
        "numero_de_operacoes": 12.0,
        "carteira_a_vencer": 30085.45,
        "a_vencer_ate_90_dias": 18942.97,
        "a_vencer_de_91_ate_360_dias": 9228.13,
        "a_vencer_de_361_ate_1080_dias": 1914.35,
        "a_vencer_de_1081_ate_1800_dias": 0.0,
        "a_vencer_de_1801_ate_5400_dias": 0.0,
        "a_vencer_acima_de_5400_dias": 0.0,
        "risk_percent": 73.12,
        "risk_status": "Alto"
    },
    {
        "id": 37,
        "nome": "Amanda Ferreira",
        "uf": "MG",
        "cnae_ocupacao": "Empresário",
        "porte": "Mais de 1 a 2 salários mínimos",
        "modalidade": "Financiamentos imobiliários",
        "submodalidade": "Crédito pessoal - sem consignação em folha de pagam.",
        "numero_de_operacoes": 11.0,
        "carteira_a_vencer": 7032.78,
        "a_vencer_ate_90_dias": 5029.29,
        "a_vencer_de_91_ate_360_dias": 510.74,
        "a_vencer_de_361_ate_1080_dias": 1492.75,
        "a_vencer_de_1081_ate_1800_dias": 0.0,
        "a_vencer_de_1801_ate_5400_dias": 0.0,
        "a_vencer_acima_de_5400_dias": 0.0,
        "risk_percent": 61.88,
        "risk_status": "Médio"
    },
    {
        "id": 38,
        "nome": "Letícia Gomes",
        "uf": "RJ",
        "cnae_ocupacao": "Servidor ou empregado público",
        "porte": "Mais de 10 a 20 salários mínimos",
        "modalidade": "Outros créditos",
        "submodalidade": "Outros",
        "numero_de_operacoes": 6.0,
        "carteira_a_vencer": 39734.5,
        "a_vencer_ate_90_dias": 31709.8,
        "a_vencer_de_91_ate_360_dias": 293.05,
        "a_vencer_de_361_ate_1080_dias": 7731.65,
        "a_vencer_de_1081_ate_1800_dias": 0.0,
        "a_vencer_de_1801_ate_5400_dias": 0.0,
        "a_vencer_acima_de_5400_dias": 0.0,
        "risk_percent": 70.73,
        "risk_status": "Alto"
    },
    {
        "id": 39,
        "nome": "Milena Martins",
        "uf": "SP",
        "cnae_ocupacao": "Empregado de empresa privada",
        "porte": "Até 1 salário mínimo",
        "modalidade": "Empréstimos",
        "submodalidade": "Crédito pessoal - sem consignação em folha de pagam.",
        "numero_de_operacoes": 16.0,
        "carteira_a_vencer": 8267.76,
        "a_vencer_ate_90_dias": 2616.57,
        "a_vencer_de_91_ate_360_dias": 3904.05,
        "a_vencer_de_361_ate_1080_dias": 1747.14,
        "a_vencer_de_1081_ate_1800_dias": 0.0,
        "a_vencer_de_1801_ate_5400_dias": 0.0,
        "a_vencer_acima_de_5400_dias": 0.0,
        "risk_percent": 81.21,
        "risk_status": "Alto"
    },
    {
        "id": 40,
        "nome": "João Gomes",
        "uf": "RS",
        "cnae_ocupacao": "Autônomo",
        "porte": "Mais de 5 a 10 salários mínimos",
        "modalidade": "Financiamentos imobiliários",
        "submodalidade": "Outros",
        "numero_de_operacoes": 18.0,
        "carteira_a_vencer": 46497.05,
        "a_vencer_ate_90_dias": 4812.43,
        "a_vencer_de_91_ate_360_dias": 6708.21,
        "a_vencer_de_361_ate_1080_dias": 34976.41,
        "a_vencer_de_1081_ate_1800_dias": 0.0,
        "a_vencer_de_1801_ate_5400_dias": 0.0,
        "a_vencer_acima_de_5400_dias": 0.0,
        "risk_percent": 51.04,
        "risk_status": "Médio"
    },
    {
        "id": 41,
        "nome": "Marcos Almeida",
        "uf": "SP",
        "cnae_ocupacao": "Outros",
        "porte": "Indisponível",
        "modalidade": "Financiamentos",
        "submodalidade": "Cheque especial",
        "numero_de_operacoes": 3.0,
        "carteira_a_vencer": 12986.04,
        "a_vencer_ate_90_dias": 375.75,
        "a_vencer_de_91_ate_360_dias": 2643.63,
        "a_vencer_de_361_ate_1080_dias": 9966.66,
        "a_vencer_de_1081_ate_1800_dias": 0.0,
        "a_vencer_de_1801_ate_5400_dias": 0.0,
        "a_vencer_acima_de_5400_dias": 0.0,
        "risk_percent": 42.71,
        "risk_status": "Médio"
    },
    {
        "id": 42,
        "nome": "Rafael Souza",
        "uf": "RS",
        "cnae_ocupacao": "Empresário",
        "porte": "Mais de 3 a 5 salários mínimos",
        "modalidade": "Outros créditos",
        "submodalidade": "Cheque especial",
        "numero_de_operacoes": 6.0,
        "carteira_a_vencer": 42438.03,
        "a_vencer_ate_90_dias": 2284.21,
        "a_vencer_de_91_ate_360_dias": 37742.66,
        "a_vencer_de_361_ate_1080_dias": 2411.16,
        "a_vencer_de_1081_ate_1800_dias": 0.0,
        "a_vencer_de_1801_ate_5400_dias": 0.0,
        "a_vencer_acima_de_5400_dias": 0.0,
        "risk_percent": 50.22,
        "risk_status": "Médio"
    },
    {
        "id": 43,
        "nome": "Rafael Almeida",
        "uf": "Outros",
        "cnae_ocupacao": "Outros",
        "porte": "Mais de 1 a 2 salários mínimos",
        "modalidade": "Financiamentos",
        "submodalidade": "Financiamento habitacional - SFH",
        "numero_de_operacoes": 12.0,
        "carteira_a_vencer": 46049.04,
        "a_vencer_ate_90_dias": 18338.11,
        "a_vencer_de_91_ate_360_dias": 12432.95,
        "a_vencer_de_361_ate_1080_dias": 15277.98,
        "a_vencer_de_1081_ate_1800_dias": 0.0,
        "a_vencer_de_1801_ate_5400_dias": 0.0,
        "a_vencer_acima_de_5400_dias": 0.0,
        "risk_percent": 83.61,
        "risk_status": "Alto"
    },
    {
        "id": 44,
        "nome": "Rodrigo Carvalho",
        "uf": "PR",
        "cnae_ocupacao": "Autônomo",
        "porte": "Mais de 2 a 3 salários mínimos",
        "modalidade": "Empréstimos",
        "submodalidade": "Crédito pessoal - sem consignação em folha de pagam.",
        "numero_de_operacoes": 18.0,
        "carteira_a_vencer": 35650.35,
        "a_vencer_ate_90_dias": 22579.66,
        "a_vencer_de_91_ate_360_dias": 7030.05,
        "a_vencer_de_361_ate_1080_dias": 6040.64,
        "a_vencer_de_1081_ate_1800_dias": 0.0,
        "a_vencer_de_1801_ate_5400_dias": 0.0,
        "a_vencer_acima_de_5400_dias": 0.0,
        "risk_percent": 84.58,
        "risk_status": "Alto"
    },
    {
        "id": 45,
        "nome": "Milena Souza",
        "uf": "PR",
        "cnae_ocupacao": "Outros",
        "porte": "Mais de 5 a 10 salários mínimos",
        "modalidade": "Empréstimos",
        "submodalidade": "Aquisição de bens - veículos automotores",
        "numero_de_operacoes": 6.0,
        "carteira_a_vencer": 28588.03,
        "a_vencer_ate_90_dias": 6507.97,
        "a_vencer_de_91_ate_360_dias": 17186.74,
        "a_vencer_de_361_ate_1080_dias": 4893.32,
        "a_vencer_de_1081_ate_1800_dias": 0.0,
        "a_vencer_de_1801_ate_5400_dias": 0.0,
        "a_vencer_acima_de_5400_dias": 0.0,
        "risk_percent": 57.21,
        "risk_status": "Médio"
    },
    {
        "id": 46,
        "nome": "João Carvalho",
        "uf": "AC",
        "cnae_ocupacao": "Empresário",
        "porte": "Mais de 5 a 10 salários mínimos",
        "modalidade": "Operações de arrendamento",
        "submodalidade": "Crédito pessoal - sem consignação em folha de pagam.",
        "numero_de_operacoes": 1.0,
        "carteira_a_vencer": 11592.47,
        "a_vencer_ate_90_dias": 2712.87,
        "a_vencer_de_91_ate_360_dias": 7165.61,
        "a_vencer_de_361_ate_1080_dias": 1713.99,
        "a_vencer_de_1081_ate_1800_dias": 0.0,
        "a_vencer_de_1801_ate_5400_dias": 0.0,
        "a_vencer_acima_de_5400_dias": 0.0,
        "risk_percent": 26.34,
        "risk_status": "Baixo"
    },
    {
        "id": 47,
        "nome": "Bruno Almeida",
        "uf": "RS",
        "cnae_ocupacao": "Servidor ou empregado público",
        "porte": "Sem rendimento",
        "modalidade": "Financiamentos",
        "submodalidade": "Crédito pessoal - sem consignação em folha de pagam.",
        "numero_de_operacoes": 12.0,
        "carteira_a_vencer": 34461.41,
        "a_vencer_ate_90_dias": 22285.67,
        "a_vencer_de_91_ate_360_dias": 10665.67,
        "a_vencer_de_361_ate_1080_dias": 1510.07,
        "a_vencer_de_1081_ate_1800_dias": 0.0,
        "a_vencer_de_1801_ate_5400_dias": 0.0,
        "a_vencer_acima_de_5400_dias": 0.0,
        "risk_percent": 74.76,
        "risk_status": "Alto"
    },
    {
        "id": 48,
        "nome": "Ana Ribeiro",
        "uf": "RJ",
        "cnae_ocupacao": "Empresário",
        "porte": "Sem rendimento",
        "modalidade": "Outros créditos",
        "submodalidade": "Outros",
        "numero_de_operacoes": 17.0,
        "carteira_a_vencer": 26263.34,
        "a_vencer_ate_90_dias": 5456.9,
        "a_vencer_de_91_ate_360_dias": 15649.68,
        "a_vencer_de_361_ate_1080_dias": 5156.76,
        "a_vencer_de_1081_ate_1800_dias": 0.0,
        "a_vencer_de_1801_ate_5400_dias": 0.0,
        "a_vencer_acima_de_5400_dias": 0.0,
        "risk_percent": 92.15,
        "risk_status": "Alto"
    },
    {
        "id": 49,
        "nome": "Juliana Santos",
        "uf": "RS",
        "cnae_ocupacao": "Autônomo",
        "porte": "Indisponível",
        "modalidade": "Financiamentos",
        "submodalidade": "Aquisição de bens - veículos automotores",
        "numero_de_operacoes": 5.0,
        "carteira_a_vencer": 9170.81,
        "a_vencer_ate_90_dias": 783.99,
        "a_vencer_de_91_ate_360_dias": 3575.5,
        "a_vencer_de_361_ate_1080_dias": 4811.32,
        "a_vencer_de_1081_ate_1800_dias": 0.0,
        "a_vencer_de_1801_ate_5400_dias": 0.0,
        "a_vencer_acima_de_5400_dias": 0.0,
        "risk_percent": 55.64,
        "risk_status": "Médio"
    },
    {
        "id": 50,
        "nome": "Pedro Santos",
        "uf": "RJ",
        "cnae_ocupacao": "MEI",
        "porte": "Sem rendimento",
        "modalidade": "Operações de arrendamento",
        "submodalidade": "Cheque especial",
        "numero_de_operacoes": 9.0,
        "carteira_a_vencer": 23693.22,
        "a_vencer_ate_90_dias": 19744.81,
        "a_vencer_de_91_ate_360_dias": 2592.96,
        "a_vencer_de_361_ate_1080_dias": 1355.45,
        "a_vencer_de_1081_ate_1800_dias": 0.0,
        "a_vencer_de_1801_ate_5400_dias": 0.0,
        "a_vencer_acima_de_5400_dias": 0.0,
        "risk_percent": 68.07,
        "risk_status": "Médio"
    },
    {
        "id": 51,
        "nome": "Marcos Souza",
        "uf": "AC",
        "cnae_ocupacao": "Autônomo",
        "porte": "Indisponível",
        "modalidade": "Empréstimos",
        "submodalidade": "Aquisição de bens - veículos automotores",
        "numero_de_operacoes": 2.0,
        "carteira_a_vencer": 7618.89,
        "a_vencer_ate_90_dias": 6181.96,
        "a_vencer_de_91_ate_360_dias": 948.41,
        "a_vencer_de_361_ate_1080_dias": 488.52,
        "a_vencer_de_1081_ate_1800_dias": 0.0,
        "a_vencer_de_1801_ate_5400_dias": 0.0,
        "a_vencer_acima_de_5400_dias": 0.0,
        "risk_percent": 39.73,
        "risk_status": "Médio"
    },
    {
        "id": 52,
        "nome": "Letícia Rodrigues",
        "uf": "SP",
        "cnae_ocupacao": "Autônomo",
        "porte": "Indisponível",
        "modalidade": "Empréstimos",
        "submodalidade": "Crédito pessoal - sem consignação em folha de pagam.",
        "numero_de_operacoes": 18.0,
        "carteira_a_vencer": 11887.0,
        "a_vencer_ate_90_dias": 2625.76,
        "a_vencer_de_91_ate_360_dias": 1935.34,
        "a_vencer_de_361_ate_1080_dias": 7325.9,
        "a_vencer_de_1081_ate_1800_dias": 0.0,
        "a_vencer_de_1801_ate_5400_dias": 0.0,
        "a_vencer_acima_de_5400_dias": 0.0,
        "risk_percent": 75.21,
        "risk_status": "Alto"
    },
    {
        "id": 53,
        "nome": "Marcos Ferreira",
        "uf": "SC",
        "cnae_ocupacao": "MEI",
        "porte": "Mais de 5 a 10 salários mínimos",
        "modalidade": "Financiamentos",
        "submodalidade": "Cheque especial",
        "numero_de_operacoes": 11.0,
        "carteira_a_vencer": 31117.91,
        "a_vencer_ate_90_dias": 3581.83,
        "a_vencer_de_91_ate_360_dias": 19588.54,
        "a_vencer_de_361_ate_1080_dias": 7947.54,
        "a_vencer_de_1081_ate_1800_dias": 0.0,
        "a_vencer_de_1801_ate_5400_dias": 0.0,
        "a_vencer_acima_de_5400_dias": 0.0,
        "risk_percent": 61.91,
        "risk_status": "Médio"
    },
    {
        "id": 54,
        "nome": "Letícia Martins",
        "uf": "AC",
        "cnae_ocupacao": "Servidor ou empregado público",
        "porte": "Mais de 1 a 2 salários mínimos",
        "modalidade": "Financiamentos",
        "submodalidade": "Crédito pessoal - com consignação em folha de pagam.",
        "numero_de_operacoes": 3.0,
        "carteira_a_vencer": 26844.46,
        "a_vencer_ate_90_dias": 15877.17,
        "a_vencer_de_91_ate_360_dias": 8527.07,
        "a_vencer_de_361_ate_1080_dias": 2440.22,
        "a_vencer_de_1081_ate_1800_dias": 0.0,
        "a_vencer_de_1801_ate_5400_dias": 0.0,
        "a_vencer_acima_de_5400_dias": 0.0,
        "risk_percent": 36.68,
        "risk_status": "Médio"
    },
    {
        "id": 55,
        "nome": "Bruno Costa",
        "uf": "MG",
        "cnae_ocupacao": "Empresário",
        "porte": "Mais de 1 a 2 salários mínimos",
        "modalidade": "Outros créditos",
        "submodalidade": "Cheque especial",
        "numero_de_operacoes": 4.0,
        "carteira_a_vencer": 7284.84,
        "a_vencer_ate_90_dias": 2931.83,
        "a_vencer_de_91_ate_360_dias": 2359.0,
        "a_vencer_de_361_ate_1080_dias": 1994.01,
        "a_vencer_de_1081_ate_1800_dias": 0.0,
        "a_vencer_de_1801_ate_5400_dias": 0.0,
        "a_vencer_acima_de_5400_dias": 0.0,
        "risk_percent": 48.57,
        "risk_status": "Médio"
    },
    {
        "id": 56,
        "nome": "Ana Santos",
        "uf": "AC",
        "cnae_ocupacao": "Servidor ou empregado público",
        "porte": "Mais de 5 a 10 salários mínimos",
        "modalidade": "Financiamentos imobiliários",
        "submodalidade": "Cheque especial",
        "numero_de_operacoes": 4.0,
        "carteira_a_vencer": 42274.47,
        "a_vencer_ate_90_dias": 21165.69,
        "a_vencer_de_91_ate_360_dias": 20682.3,
        "a_vencer_de_361_ate_1080_dias": 426.48,
        "a_vencer_de_1081_ate_1800_dias": 0.0,
        "a_vencer_de_1801_ate_5400_dias": 0.0,
        "a_vencer_acima_de_5400_dias": 0.0,
        "risk_percent": 37.27,
        "risk_status": "Médio"
    },
    {
        "id": 57,
        "nome": "Amanda Souza",
        "uf": "RS",
        "cnae_ocupacao": "Empresário",
        "porte": "Indisponível",
        "modalidade": "Outros créditos",
        "submodalidade": "Crédito pessoal - com consignação em folha de pagam.",
        "numero_de_operacoes": 8.0,
        "carteira_a_vencer": 5570.25,
        "a_vencer_ate_90_dias": 3470.64,
        "a_vencer_de_91_ate_360_dias": 1684.33,
        "a_vencer_de_361_ate_1080_dias": 415.28,
        "a_vencer_de_1081_ate_1800_dias": 0.0,
        "a_vencer_de_1801_ate_5400_dias": 0.0,
        "a_vencer_acima_de_5400_dias": 0.0,
        "risk_percent": 66.71,
        "risk_status": "Médio"
    },
    {
        "id": 58,
        "nome": "Pedro Almeida",
        "uf": "MG",
        "cnae_ocupacao": "Servidor ou empregado público",
        "porte": "Mais de 5 a 10 salários mínimos",
        "modalidade": "Financiamentos imobiliários",
        "submodalidade": "Aquisição de bens - veículos automotores",
        "numero_de_operacoes": 13.0,
        "carteira_a_vencer": 22194.66,
        "a_vencer_ate_90_dias": 18516.48,
        "a_vencer_de_91_ate_360_dias": 343.2,
        "a_vencer_de_361_ate_1080_dias": 3334.98,
        "a_vencer_de_1081_ate_1800_dias": 0.0,
        "a_vencer_de_1801_ate_5400_dias": 0.0,
        "a_vencer_acima_de_5400_dias": 0.0,
        "risk_percent": 61.0,
        "risk_status": "Médio"
    },
    {
        "id": 59,
        "nome": "Rodrigo Costa",
        "uf": "SP",
        "cnae_ocupacao": "MEI",
        "porte": "Mais de 1 a 2 salários mínimos",
        "modalidade": "Financiamentos",
        "submodalidade": "Aquisição de bens - veículos automotores",
        "numero_de_operacoes": 8.0,
        "carteira_a_vencer": 34902.61,
        "a_vencer_ate_90_dias": 3522.6,
        "a_vencer_de_91_ate_360_dias": 24588.17,
        "a_vencer_de_361_ate_1080_dias": 6791.84,
        "a_vencer_de_1081_ate_1800_dias": 0.0,
        "a_vencer_de_1801_ate_5400_dias": 0.0,
        "a_vencer_acima_de_5400_dias": 0.0,
        "risk_percent": 62.42,
        "risk_status": "Médio"
    },
    {
        "id": 60,
        "nome": "Carlos Ferreira",
        "uf": "Outros",
        "cnae_ocupacao": "Empregado de empresa privada",
        "porte": "Mais de 5 a 10 salários mínimos",
        "modalidade": "Financiamentos",
        "submodalidade": "Cheque especial",
        "numero_de_operacoes": 18.0,
        "carteira_a_vencer": 12655.12,
        "a_vencer_ate_90_dias": 524.3,
        "a_vencer_de_91_ate_360_dias": 1601.02,
        "a_vencer_de_361_ate_1080_dias": 10529.8,
        "a_vencer_de_1081_ate_1800_dias": 0.0,
        "a_vencer_de_1801_ate_5400_dias": 0.0,
        "a_vencer_acima_de_5400_dias": 0.0,
        "risk_percent": 67.46,
        "risk_status": "Médio"
    },
    {
        "id": 61,
        "nome": "Lucas Lima",
        "uf": "SC",
        "cnae_ocupacao": "Empregado de empresa privada",
        "porte": "Até 1 salário mínimo",
        "modalidade": "Operações de arrendamento",
        "submodalidade": "Outros",
        "numero_de_operacoes": 3.0,
        "carteira_a_vencer": 49574.68,
        "a_vencer_ate_90_dias": 31473.19,
        "a_vencer_de_91_ate_360_dias": 6585.89,
        "a_vencer_de_361_ate_1080_dias": 11515.6,
        "a_vencer_de_1081_ate_1800_dias": 0.0,
        "a_vencer_de_1801_ate_5400_dias": 0.0,
        "a_vencer_acima_de_5400_dias": 0.0,
        "risk_percent": 34.3,
        "risk_status": "Médio"
    },
    {
        "id": 62,
        "nome": "Milena Silva",
        "uf": "AC",
        "cnae_ocupacao": "Empresário",
        "porte": "Sem rendimento",
        "modalidade": "Empréstimos",
        "submodalidade": "Crédito pessoal - com consignação em folha de pagam.",
        "numero_de_operacoes": 16.0,
        "carteira_a_vencer": 14579.1,
        "a_vencer_ate_90_dias": 1261.28,
        "a_vencer_de_91_ate_360_dias": 410.16,
        "a_vencer_de_361_ate_1080_dias": 12907.66,
        "a_vencer_de_1081_ate_1800_dias": 0.0,
        "a_vencer_de_1801_ate_5400_dias": 0.0,
        "a_vencer_acima_de_5400_dias": 0.0,
        "risk_percent": 73.51,
        "risk_status": "Alto"
    },
    {
        "id": 63,
        "nome": "João Almeida",
        "uf": "SC",
        "cnae_ocupacao": "Empresário",
        "porte": "Mais de 2 a 3 salários mínimos",
        "modalidade": "Financiamentos imobiliários",
        "submodalidade": "Crédito pessoal - com consignação em folha de pagam.",
        "numero_de_operacoes": 2.0,
        "carteira_a_vencer": 36671.4,
        "a_vencer_ate_90_dias": 32352.7,
        "a_vencer_de_91_ate_360_dias": 3019.88,
        "a_vencer_de_361_ate_1080_dias": 1298.82,
        "a_vencer_de_1081_ate_1800_dias": 0.0,
        "a_vencer_de_1801_ate_5400_dias": 0.0,
        "a_vencer_acima_de_5400_dias": 0.0,
        "risk_percent": 26.78,
        "risk_status": "Baixo"
    },
    {
        "id": 64,
        "nome": "Rafael Costa",
        "uf": "RS",
        "cnae_ocupacao": "Autônomo",
        "porte": "Mais de 10 a 20 salários mínimos",
        "modalidade": "Financiamentos",
        "submodalidade": "Crédito pessoal - sem consignação em folha de pagam.",
        "numero_de_operacoes": 1.0,
        "carteira_a_vencer": 20241.76,
        "a_vencer_ate_90_dias": 16478.35,
        "a_vencer_de_91_ate_360_dias": 3047.89,
        "a_vencer_de_361_ate_1080_dias": 715.52,
        "a_vencer_de_1081_ate_1800_dias": 0.0,
        "a_vencer_de_1801_ate_5400_dias": 0.0,
        "a_vencer_acima_de_5400_dias": 0.0,
        "risk_percent": 26.98,
        "risk_status": "Baixo"
    },
    {
        "id": 65,
        "nome": "Carlos Almeida",
        "uf": "AC",
        "cnae_ocupacao": "Empregado de empresa privada",
        "porte": "Mais de 2 a 3 salários mínimos",
        "modalidade": "Empréstimos",
        "submodalidade": "Cheque especial",
        "numero_de_operacoes": 19.0,
        "carteira_a_vencer": 10873.86,
        "a_vencer_ate_90_dias": 9504.63,
        "a_vencer_de_91_ate_360_dias": 1137.07,
        "a_vencer_de_361_ate_1080_dias": 232.16,
        "a_vencer_de_1081_ate_1800_dias": 0.0,
        "a_vencer_de_1801_ate_5400_dias": 0.0,
        "a_vencer_acima_de_5400_dias": 0.0,
        "risk_percent": 88.35,
        "risk_status": "Alto"
    },
    {
        "id": 66,
        "nome": "Carlos Oliveira",
        "uf": "PR",
        "cnae_ocupacao": "MEI",
        "porte": "Mais de 1 a 2 salários mínimos",
        "modalidade": "Financiamentos imobiliários",
        "submodalidade": "Outros",
        "numero_de_operacoes": 19.0,
        "carteira_a_vencer": 43240.64,
        "a_vencer_ate_90_dias": 24961.3,
        "a_vencer_de_91_ate_360_dias": 5119.77,
        "a_vencer_de_361_ate_1080_dias": 13159.57,
        "a_vencer_de_1081_ate_1800_dias": 0.0,
        "a_vencer_de_1801_ate_5400_dias": 0.0,
        "a_vencer_acima_de_5400_dias": 0.0,
        "risk_percent": 58.0,
        "risk_status": "Médio"
    },
    {
        "id": 67,
        "nome": "Ana Oliveira",
        "uf": "MG",
        "cnae_ocupacao": "Servidor ou empregado público",
        "porte": "Mais de 1 a 2 salários mínimos",
        "modalidade": "Financiamentos",
        "submodalidade": "Outros",
        "numero_de_operacoes": 13.0,
        "carteira_a_vencer": 44643.44,
        "a_vencer_ate_90_dias": 23486.62,
        "a_vencer_de_91_ate_360_dias": 6341.56,
        "a_vencer_de_361_ate_1080_dias": 14815.26,
        "a_vencer_de_1081_ate_1800_dias": 0.0,
        "a_vencer_de_1801_ate_5400_dias": 0.0,
        "a_vencer_acima_de_5400_dias": 0.0,
        "risk_percent": 63.05,
        "risk_status": "Médio"
    },
    {
        "id": 68,
        "nome": "Camila Ferreira",
        "uf": "AC",
        "cnae_ocupacao": "Autônomo",
        "porte": "Mais de 1 a 2 salários mínimos",
        "modalidade": "Outros créditos",
        "submodalidade": "Financiamento habitacional - SFH",
        "numero_de_operacoes": 17.0,
        "carteira_a_vencer": 4582.8,
        "a_vencer_ate_90_dias": 1373.05,
        "a_vencer_de_91_ate_360_dias": 1058.65,
        "a_vencer_de_361_ate_1080_dias": 2151.1,
        "a_vencer_de_1081_ate_1800_dias": 0.0,
        "a_vencer_de_1801_ate_5400_dias": 0.0,
        "a_vencer_acima_de_5400_dias": 0.0,
        "risk_percent": 71.53,
        "risk_status": "Alto"
    },
    {
        "id": 69,
        "nome": "Fernanda Lima",
        "uf": "Outros",
        "cnae_ocupacao": "Empresário",
        "porte": "Mais de 10 a 20 salários mínimos",
        "modalidade": "Financiamentos imobiliários",
        "submodalidade": "Crédito pessoal - com consignação em folha de pagam.",
        "numero_de_operacoes": 16.0,
        "carteira_a_vencer": 10811.5,
        "a_vencer_ate_90_dias": 406.12,
        "a_vencer_de_91_ate_360_dias": 1402.47,
        "a_vencer_de_361_ate_1080_dias": 9002.91,
        "a_vencer_de_1081_ate_1800_dias": 0.0,
        "a_vencer_de_1801_ate_5400_dias": 0.0,
        "a_vencer_acima_de_5400_dias": 0.0,
        "risk_percent": 57.98,
        "risk_status": "Médio"
    },
    {
        "id": 70,
        "nome": "Ana Carvalho",
        "uf": "MG",
        "cnae_ocupacao": "Empresário",
        "porte": "Mais de 1 a 2 salários mínimos",
        "modalidade": "Operações de arrendamento",
        "submodalidade": "Financiamento habitacional - SFH",
        "numero_de_operacoes": 9.0,
        "carteira_a_vencer": 36561.19,
        "a_vencer_ate_90_dias": 32043.48,
        "a_vencer_de_91_ate_360_dias": 4010.92,
        "a_vencer_de_361_ate_1080_dias": 506.79,
        "a_vencer_de_1081_ate_1800_dias": 0.0,
        "a_vencer_de_1801_ate_5400_dias": 0.0,
        "a_vencer_acima_de_5400_dias": 0.0,
        "risk_percent": 59.33,
        "risk_status": "Médio"
    },
    {
        "id": 71,
        "nome": "Juliana Rodrigues",
        "uf": "AC",
        "cnae_ocupacao": "MEI",
        "porte": "Até 1 salário mínimo",
        "modalidade": "Empréstimos",
        "submodalidade": "Financiamento habitacional - SFH",
        "numero_de_operacoes": 4.0,
        "carteira_a_vencer": 47164.71,
        "a_vencer_ate_90_dias": 2467.27,
        "a_vencer_de_91_ate_360_dias": 22404.37,
        "a_vencer_de_361_ate_1080_dias": 22293.07,
        "a_vencer_de_1081_ate_1800_dias": 0.0,
        "a_vencer_de_1801_ate_5400_dias": 0.0,
        "a_vencer_acima_de_5400_dias": 0.0,
        "risk_percent": 41.09,
        "risk_status": "Médio"
    },
    {
        "id": 72,
        "nome": "Pedro Costa",
        "uf": "RS",
        "cnae_ocupacao": "Servidor ou empregado público",
        "porte": "Sem rendimento",
        "modalidade": "Financiamentos imobiliários",
        "submodalidade": "Crédito pessoal - sem consignação em folha de pagam.",
        "numero_de_operacoes": 1.0,
        "carteira_a_vencer": 22657.47,
        "a_vencer_ate_90_dias": 6664.34,
        "a_vencer_de_91_ate_360_dias": 6129.66,
        "a_vencer_de_361_ate_1080_dias": 9863.47,
        "a_vencer_de_1081_ate_1800_dias": 0.0,
        "a_vencer_de_1801_ate_5400_dias": 0.0,
        "a_vencer_acima_de_5400_dias": 0.0,
        "risk_percent": 32.05,
        "risk_status": "Médio"
    },
    {
        "id": 73,
        "nome": "Carlos Lima",
        "uf": "RS",
        "cnae_ocupacao": "Servidor ou empregado público",
        "porte": "Mais de 10 a 20 salários mínimos",
        "modalidade": "Financiamentos",
        "submodalidade": "Aquisição de bens - veículos automotores",
        "numero_de_operacoes": 5.0,
        "carteira_a_vencer": 11051.66,
        "a_vencer_ate_90_dias": 9419.79,
        "a_vencer_de_91_ate_360_dias": 824.24,
        "a_vencer_de_361_ate_1080_dias": 807.63,
        "a_vencer_de_1081_ate_1800_dias": 0.0,
        "a_vencer_de_1801_ate_5400_dias": 0.0,
        "a_vencer_acima_de_5400_dias": 0.0,
        "risk_percent": 52.16,
        "risk_status": "Médio"
    },
    {
        "id": 74,
        "nome": "Carlos Lima",
        "uf": "RS",
        "cnae_ocupacao": "Empregado de empresa privada",
        "porte": "Mais de 1 a 2 salários mínimos",
        "modalidade": "Financiamentos imobiliários",
        "submodalidade": "Outros",
        "numero_de_operacoes": 13.0,
        "carteira_a_vencer": 12271.85,
        "a_vencer_ate_90_dias": 1994.2,
        "a_vencer_de_91_ate_360_dias": 7156.7,
        "a_vencer_de_361_ate_1080_dias": 3120.95,
        "a_vencer_de_1081_ate_1800_dias": 0.0,
        "a_vencer_de_1801_ate_5400_dias": 0.0,
        "a_vencer_acima_de_5400_dias": 0.0,
        "risk_percent": 51.74,
        "risk_status": "Médio"
    },
    {
        "id": 75,
        "nome": "João Rodrigues",
        "uf": "Outros",
        "cnae_ocupacao": "Empresário",
        "porte": "Mais de 1 a 2 salários mínimos",
        "modalidade": "Financiamentos imobiliários",
        "submodalidade": "Crédito pessoal - sem consignação em folha de pagam.",
        "numero_de_operacoes": 20.0,
        "carteira_a_vencer": 33907.67,
        "a_vencer_ate_90_dias": 16947.51,
        "a_vencer_de_91_ate_360_dias": 721.22,
        "a_vencer_de_361_ate_1080_dias": 16238.94,
        "a_vencer_de_1081_ate_1800_dias": 0.0,
        "a_vencer_de_1801_ate_5400_dias": 0.0,
        "a_vencer_acima_de_5400_dias": 0.0,
        "risk_percent": 62.77,
        "risk_status": "Médio"
    },
    {
        "id": 76,
        "nome": "Rafael Ferreira",
        "uf": "AC",
        "cnae_ocupacao": "Empregado de empresa privada",
        "porte": "Sem rendimento",
        "modalidade": "Financiamentos",
        "submodalidade": "Crédito pessoal - com consignação em folha de pagam.",
        "numero_de_operacoes": 10.0,
        "carteira_a_vencer": 1391.3,
        "a_vencer_ate_90_dias": 850.4,
        "a_vencer_de_91_ate_360_dias": 507.33,
        "a_vencer_de_361_ate_1080_dias": 33.57,
        "a_vencer_de_1081_ate_1800_dias": 0.0,
        "a_vencer_de_1801_ate_5400_dias": 0.0,
        "a_vencer_acima_de_5400_dias": 0.0,
        "risk_percent": 79.68,
        "risk_status": "Alto"
    },
    {
        "id": 77,
        "nome": "Lucas Martins",
        "uf": "PR",
        "cnae_ocupacao": "Autônomo",
        "porte": "Mais de 2 a 3 salários mínimos",
        "modalidade": "Empréstimos",
        "submodalidade": "Crédito pessoal - sem consignação em folha de pagam.",
        "numero_de_operacoes": 16.0,
        "carteira_a_vencer": 7873.71,
        "a_vencer_ate_90_dias": 1384.59,
        "a_vencer_de_91_ate_360_dias": 3781.34,
        "a_vencer_de_361_ate_1080_dias": 2707.78,
        "a_vencer_de_1081_ate_1800_dias": 0.0,
        "a_vencer_de_1801_ate_5400_dias": 0.0,
        "a_vencer_acima_de_5400_dias": 0.0,
        "risk_percent": 77.53,
        "risk_status": "Alto"
    },
    {
        "id": 78,
        "nome": "Ana Lima",
        "uf": "MG",
        "cnae_ocupacao": "Autônomo",
        "porte": "Mais de 3 a 5 salários mínimos",
        "modalidade": "Empréstimos",
        "submodalidade": "Crédito pessoal - sem consignação em folha de pagam.",
        "numero_de_operacoes": 8.0,
        "carteira_a_vencer": 24025.12,
        "a_vencer_ate_90_dias": 627.65,
        "a_vencer_de_91_ate_360_dias": 15182.53,
        "a_vencer_de_361_ate_1080_dias": 8214.94,
        "a_vencer_de_1081_ate_1800_dias": 0.0,
        "a_vencer_de_1801_ate_5400_dias": 0.0,
        "a_vencer_acima_de_5400_dias": 0.0,
        "risk_percent": 62.83,
        "risk_status": "Médio"
    },
    {
        "id": 79,
        "nome": "Ana Rodrigues",
        "uf": "RS",
        "cnae_ocupacao": "Empresário",
        "porte": "Até 1 salário mínimo",
        "modalidade": "Financiamentos imobiliários",
        "submodalidade": "Financiamento habitacional - SFH",
        "numero_de_operacoes": 15.0,
        "carteira_a_vencer": 27954.85,
        "a_vencer_ate_90_dias": 7342.78,
        "a_vencer_de_91_ate_360_dias": 20260.73,
        "a_vencer_de_361_ate_1080_dias": 351.34,
        "a_vencer_de_1081_ate_1800_dias": 0.0,
        "a_vencer_de_1801_ate_5400_dias": 0.0,
        "a_vencer_acima_de_5400_dias": 0.0,
        "risk_percent": 53.18,
        "risk_status": "Médio"
    },
    {
        "id": 80,
        "nome": "Bruno Pereira",
        "uf": "AC",
        "cnae_ocupacao": "Empregado de empresa privada",
        "porte": "Mais de 10 a 20 salários mínimos",
        "modalidade": "Operações de arrendamento",
        "submodalidade": "Outros",
        "numero_de_operacoes": 1.0,
        "carteira_a_vencer": 27313.81,
        "a_vencer_ate_90_dias": 4771.58,
        "a_vencer_de_91_ate_360_dias": 11924.0,
        "a_vencer_de_361_ate_1080_dias": 10618.23,
        "a_vencer_de_1081_ate_1800_dias": 0.0,
        "a_vencer_de_1801_ate_5400_dias": 0.0,
        "a_vencer_acima_de_5400_dias": 0.0,
        "risk_percent": 21.68,
        "risk_status": "Baixo"
    },
    {
        "id": 81,
        "nome": "Camila Oliveira",
        "uf": "SP",
        "cnae_ocupacao": "Empregado de empresa privada",
        "porte": "Até 1 salário mínimo",
        "modalidade": "Empréstimos",
        "submodalidade": "Cartão de crédito - compra, fatura parcelada ou saque financiado pela instituição financeira emitente do cartão",
        "numero_de_operacoes": 2.0,
        "carteira_a_vencer": 41169.3,
        "a_vencer_ate_90_dias": 29763.86,
        "a_vencer_de_91_ate_360_dias": 2679.37,
        "a_vencer_de_361_ate_1080_dias": 8726.07,
        "a_vencer_de_1081_ate_1800_dias": 0.0,
        "a_vencer_de_1801_ate_5400_dias": 0.0,
        "a_vencer_acima_de_5400_dias": 0.0,
        "risk_percent": 49.54,
        "risk_status": "Médio"
    },
    {
        "id": 82,
        "nome": "Milena Almeida",
        "uf": "SC",
        "cnae_ocupacao": "Autônomo",
        "porte": "Mais de 2 a 3 salários mínimos",
        "modalidade": "Financiamentos",
        "submodalidade": "Outros",
        "numero_de_operacoes": 13.0,
        "carteira_a_vencer": 10286.15,
        "a_vencer_ate_90_dias": 824.25,
        "a_vencer_de_91_ate_360_dias": 5443.94,
        "a_vencer_de_361_ate_1080_dias": 4017.96,
        "a_vencer_de_1081_ate_1800_dias": 0.0,
        "a_vencer_de_1801_ate_5400_dias": 0.0,
        "a_vencer_acima_de_5400_dias": 0.0,
        "risk_percent": 49.65,
        "risk_status": "Médio"
    },
    {
        "id": 83,
        "nome": "Rafael Almeida",
        "uf": "AC",
        "cnae_ocupacao": "Empresário",
        "porte": "Mais de 2 a 3 salários mínimos",
        "modalidade": "Financiamentos",
        "submodalidade": "Cheque especial",
        "numero_de_operacoes": 16.0,
        "carteira_a_vencer": 1525.72,
        "a_vencer_ate_90_dias": 889.88,
        "a_vencer_de_91_ate_360_dias": 521.12,
        "a_vencer_de_361_ate_1080_dias": 114.72,
        "a_vencer_de_1081_ate_1800_dias": 0.0,
        "a_vencer_de_1801_ate_5400_dias": 0.0,
        "a_vencer_acima_de_5400_dias": 0.0,
        "risk_percent": 91.82,
        "risk_status": "Alto"
    },
    {
        "id": 84,
        "nome": "Amanda Pereira",
        "uf": "RS",
        "cnae_ocupacao": "Autônomo",
        "porte": "Mais de 10 a 20 salários mínimos",
        "modalidade": "Financiamentos imobiliários",
        "submodalidade": "Aquisição de bens - veículos automotores",
        "numero_de_operacoes": 1.0,
        "carteira_a_vencer": 30155.29,
        "a_vencer_ate_90_dias": 25057.37,
        "a_vencer_de_91_ate_360_dias": 1513.68,
        "a_vencer_de_361_ate_1080_dias": 3584.24,
        "a_vencer_de_1081_ate_1800_dias": 0.0,
        "a_vencer_de_1801_ate_5400_dias": 0.0,
        "a_vencer_acima_de_5400_dias": 0.0,
        "risk_percent": 24.29,
        "risk_status": "Baixo"
    },
    {
        "id": 85,
        "nome": "Letícia Costa",
        "uf": "Outros",
        "cnae_ocupacao": "Outros",
        "porte": "Sem rendimento",
        "modalidade": "Financiamentos",
        "submodalidade": "Financiamento habitacional - SFH",
        "numero_de_operacoes": 14.0,
        "carteira_a_vencer": 16587.82,
        "a_vencer_ate_90_dias": 5062.91,
        "a_vencer_de_91_ate_360_dias": 3880.73,
        "a_vencer_de_361_ate_1080_dias": 7644.18,
        "a_vencer_de_1081_ate_1800_dias": 0.0,
        "a_vencer_de_1801_ate_5400_dias": 0.0,
        "a_vencer_acima_de_5400_dias": 0.0,
        "risk_percent": 73.82,
        "risk_status": "Alto"
    },
    {
        "id": 86,
        "nome": "Amanda Costa",
        "uf": "SC",
        "cnae_ocupacao": "Empresário",
        "porte": "Mais de 2 a 3 salários mínimos",
        "modalidade": "Outros créditos",
        "submodalidade": "Cartão de crédito - compra, fatura parcelada ou saque financiado pela instituição financeira emitente do cartão",
        "numero_de_operacoes": 19.0,
        "carteira_a_vencer": 19969.52,
        "a_vencer_ate_90_dias": 17012.28,
        "a_vencer_de_91_ate_360_dias": 859.91,
        "a_vencer_de_361_ate_1080_dias": 2097.33,
        "a_vencer_de_1081_ate_1800_dias": 0.0,
        "a_vencer_de_1801_ate_5400_dias": 0.0,
        "a_vencer_acima_de_5400_dias": 0.0,
        "risk_percent": 79.23,
        "risk_status": "Alto"
    },
    {
        "id": 87,
        "nome": "Rodrigo Ribeiro",
        "uf": "SP",
        "cnae_ocupacao": "Empresário",
        "porte": "Mais de 1 a 2 salários mínimos",
        "modalidade": "Financiamentos",
        "submodalidade": "Aquisição de bens - veículos automotores",
        "numero_de_operacoes": 1.0,
        "carteira_a_vencer": 12544.23,
        "a_vencer_ate_90_dias": 11678.19,
        "a_vencer_de_91_ate_360_dias": 244.74,
        "a_vencer_de_361_ate_1080_dias": 621.3,
        "a_vencer_de_1081_ate_1800_dias": 0.0,
        "a_vencer_de_1801_ate_5400_dias": 0.0,
        "a_vencer_acima_de_5400_dias": 0.0,
        "risk_percent": 49.6,
        "risk_status": "Médio"
    },
    {
        "id": 88,
        "nome": "Rodrigo Ribeiro",
        "uf": "SP",
        "cnae_ocupacao": "Empregado de empresa privada",
        "porte": "Mais de 5 a 10 salários mínimos",
        "modalidade": "Operações de arrendamento",
        "submodalidade": "Cartão de crédito - compra, fatura parcelada ou saque financiado pela instituição financeira emitente do cartão",
        "numero_de_operacoes": 14.0,
        "carteira_a_vencer": 203.05,
        "a_vencer_ate_90_dias": 187.8,
        "a_vencer_de_91_ate_360_dias": 14.94,
        "a_vencer_de_361_ate_1080_dias": 0.31,
        "a_vencer_de_1081_ate_1800_dias": 0.0,
        "a_vencer_de_1801_ate_5400_dias": 0.0,
        "a_vencer_acima_de_5400_dias": 0.0,
        "risk_percent": 84.42,
        "risk_status": "Alto"
    },
    {
        "id": 89,
        "nome": "Bruno Almeida",
        "uf": "AC",
        "cnae_ocupacao": "Outros",
        "porte": "Indisponível",
        "modalidade": "Empréstimos",
        "submodalidade": "Financiamento habitacional - SFH",
        "numero_de_operacoes": 1.0,
        "carteira_a_vencer": 8039.38,
        "a_vencer_ate_90_dias": 931.53,
        "a_vencer_de_91_ate_360_dias": 4406.9,
        "a_vencer_de_361_ate_1080_dias": 2700.95,
        "a_vencer_de_1081_ate_1800_dias": 0.0,
        "a_vencer_de_1801_ate_5400_dias": 0.0,
        "a_vencer_acima_de_5400_dias": 0.0,
        "risk_percent": 19.46,
        "risk_status": "Baixo"
    },
    {
        "id": 90,
        "nome": "Amanda Alves",
        "uf": "SC",
        "cnae_ocupacao": "Outros",
        "porte": "Sem rendimento",
        "modalidade": "Operações de arrendamento",
        "submodalidade": "Crédito pessoal - sem consignação em folha de pagam.",
        "numero_de_operacoes": 5.0,
        "carteira_a_vencer": 15243.15,
        "a_vencer_ate_90_dias": 7747.84,
        "a_vencer_de_91_ate_360_dias": 3919.96,
        "a_vencer_de_361_ate_1080_dias": 3575.35,
        "a_vencer_de_1081_ate_1800_dias": 0.0,
        "a_vencer_de_1801_ate_5400_dias": 0.0,
        "a_vencer_acima_de_5400_dias": 0.0,
        "risk_percent": 64.19,
        "risk_status": "Médio"
    },
    {
        "id": 91,
        "nome": "Pedro Souza",
        "uf": "RJ",
        "cnae_ocupacao": "Outros",
        "porte": "Mais de 2 a 3 salários mínimos",
        "modalidade": "Empréstimos",
        "submodalidade": "Cheque especial",
        "numero_de_operacoes": 19.0,
        "carteira_a_vencer": 47805.06,
        "a_vencer_ate_90_dias": 45940.91,
        "a_vencer_de_91_ate_360_dias": 2.85,
        "a_vencer_de_361_ate_1080_dias": 1861.3,
        "a_vencer_de_1081_ate_1800_dias": 0.0,
        "a_vencer_de_1801_ate_5400_dias": 0.0,
        "a_vencer_acima_de_5400_dias": 0.0,
        "risk_percent": 74.36,
        "risk_status": "Alto"
    },
    {
        "id": 92,
        "nome": "João Alves",
        "uf": "MG",
        "cnae_ocupacao": "MEI",
        "porte": "Indisponível",
        "modalidade": "Empréstimos",
        "submodalidade": "Financiamento habitacional - SFH",
        "numero_de_operacoes": 14.0,
        "carteira_a_vencer": 42975.9,
        "a_vencer_ate_90_dias": 10381.64,
        "a_vencer_de_91_ate_360_dias": 4338.35,
        "a_vencer_de_361_ate_1080_dias": 28255.91,
        "a_vencer_de_1081_ate_1800_dias": 0.0,
        "a_vencer_de_1801_ate_5400_dias": 0.0,
        "a_vencer_acima_de_5400_dias": 0.0,
        "risk_percent": 63.88,
        "risk_status": "Médio"
    },
    {
        "id": 93,
        "nome": "Fernanda Carvalho",
        "uf": "SP",
        "cnae_ocupacao": "Empresário",
        "porte": "Mais de 10 a 20 salários mínimos",
        "modalidade": "Empréstimos",
        "submodalidade": "Cartão de crédito - compra, fatura parcelada ou saque financiado pela instituição financeira emitente do cartão",
        "numero_de_operacoes": 20.0,
        "carteira_a_vencer": 39892.31,
        "a_vencer_ate_90_dias": 4905.45,
        "a_vencer_de_91_ate_360_dias": 12757.61,
        "a_vencer_de_361_ate_1080_dias": 22229.25,
        "a_vencer_de_1081_ate_1800_dias": 0.0,
        "a_vencer_de_1801_ate_5400_dias": 0.0,
        "a_vencer_acima_de_5400_dias": 0.0,
        "risk_percent": 67.98,
        "risk_status": "Médio"
    },
    {
        "id": 94,
        "nome": "Ana Costa",
        "uf": "RJ",
        "cnae_ocupacao": "Servidor ou empregado público",
        "porte": "Mais de 3 a 5 salários mínimos",
        "modalidade": "Operações de arrendamento",
        "submodalidade": "Crédito pessoal - com consignação em folha de pagam.",
        "numero_de_operacoes": 3.0,
        "carteira_a_vencer": 4390.78,
        "a_vencer_ate_90_dias": 2407.53,
        "a_vencer_de_91_ate_360_dias": 1847.3,
        "a_vencer_de_361_ate_1080_dias": 135.95,
        "a_vencer_de_1081_ate_1800_dias": 0.0,
        "a_vencer_de_1801_ate_5400_dias": 0.0,
        "a_vencer_acima_de_5400_dias": 0.0,
        "risk_percent": 58.97,
        "risk_status": "Médio"
    },
    {
        "id": 95,
        "nome": "Milena Gomes",
        "uf": "RJ",
        "cnae_ocupacao": "Empresário",
        "porte": "Mais de 3 a 5 salários mínimos",
        "modalidade": "Empréstimos",
        "submodalidade": "Cheque especial",
        "numero_de_operacoes": 7.0,
        "carteira_a_vencer": 48600.12,
        "a_vencer_ate_90_dias": 2234.23,
        "a_vencer_de_91_ate_360_dias": 4637.23,
        "a_vencer_de_361_ate_1080_dias": 41728.66,
        "a_vencer_de_1081_ate_1800_dias": 0.0,
        "a_vencer_de_1801_ate_5400_dias": 0.0,
        "a_vencer_acima_de_5400_dias": 0.0,
        "risk_percent": 60.07,
        "risk_status": "Médio"
    },
    {
        "id": 96,
        "nome": "Milena Costa",
        "uf": "SP",
        "cnae_ocupacao": "Servidor ou empregado público",
        "porte": "Mais de 1 a 2 salários mínimos",
        "modalidade": "Empréstimos",
        "submodalidade": "Aquisição de bens - veículos automotores",
        "numero_de_operacoes": 7.0,
        "carteira_a_vencer": 21365.01,
        "a_vencer_ate_90_dias": 16688.16,
        "a_vencer_de_91_ate_360_dias": 2209.99,
        "a_vencer_de_361_ate_1080_dias": 2466.86,
        "a_vencer_de_1081_ate_1800_dias": 0.0,
        "a_vencer_de_1801_ate_5400_dias": 0.0,
        "a_vencer_acima_de_5400_dias": 0.0,
        "risk_percent": 67.28,
        "risk_status": "Médio"
    },
    {
        "id": 97,
        "nome": "Juliana Pereira",
        "uf": "RS",
        "cnae_ocupacao": "Outros",
        "porte": "Mais de 2 a 3 salários mínimos",
        "modalidade": "Financiamentos imobiliários",
        "submodalidade": "Cheque especial",
        "numero_de_operacoes": 3.0,
        "carteira_a_vencer": 13696.08,
        "a_vencer_ate_90_dias": 5543.95,
        "a_vencer_de_91_ate_360_dias": 1546.94,
        "a_vencer_de_361_ate_1080_dias": 6605.19,
        "a_vencer_de_1081_ate_1800_dias": 0.0,
        "a_vencer_de_1801_ate_5400_dias": 0.0,
        "a_vencer_acima_de_5400_dias": 0.0,
        "risk_percent": 39.72,
        "risk_status": "Médio"
    },
    {
        "id": 98,
        "nome": "Pedro Ferreira",
        "uf": "SC",
        "cnae_ocupacao": "Servidor ou empregado público",
        "porte": "Mais de 1 a 2 salários mínimos",
        "modalidade": "Financiamentos imobiliários",
        "submodalidade": "Outros",
        "numero_de_operacoes": 3.0,
        "carteira_a_vencer": 43903.85,
        "a_vencer_ate_90_dias": 25714.14,
        "a_vencer_de_91_ate_360_dias": 17918.76,
        "a_vencer_de_361_ate_1080_dias": 270.95,
        "a_vencer_de_1081_ate_1800_dias": 0.0,
        "a_vencer_de_1801_ate_5400_dias": 0.0,
        "a_vencer_acima_de_5400_dias": 0.0,
        "risk_percent": 31.56,
        "risk_status": "Médio"
    },
    {
        "id": 99,
        "nome": "Carlos Carvalho",
        "uf": "RJ",
        "cnae_ocupacao": "Servidor ou empregado público",
        "porte": "Mais de 2 a 3 salários mínimos",
        "modalidade": "Financiamentos imobiliários",
        "submodalidade": "Cartão de crédito - compra, fatura parcelada ou saque financiado pela instituição financeira emitente do cartão",
        "numero_de_operacoes": 19.0,
        "carteira_a_vencer": 43846.45,
        "a_vencer_ate_90_dias": 32300.86,
        "a_vencer_de_91_ate_360_dias": 9421.05,
        "a_vencer_de_361_ate_1080_dias": 2124.54,
        "a_vencer_de_1081_ate_1800_dias": 0.0,
        "a_vencer_de_1801_ate_5400_dias": 0.0,
        "a_vencer_acima_de_5400_dias": 0.0,
        "risk_percent": 60.36,
        "risk_status": "Médio"
    },
    {
        "id": 100,
        "nome": "Ana Gomes",
        "uf": "SP",
        "cnae_ocupacao": "Outros",
        "porte": "Sem rendimento",
        "modalidade": "Operações de arrendamento",
        "submodalidade": "Cartão de crédito - compra, fatura parcelada ou saque financiado pela instituição financeira emitente do cartão",
        "numero_de_operacoes": 8.0,
        "carteira_a_vencer": 43167.9,
        "a_vencer_ate_90_dias": 18443.99,
        "a_vencer_de_91_ate_360_dias": 7463.08,
        "a_vencer_de_361_ate_1080_dias": 17260.83,
        "a_vencer_de_1081_ate_1800_dias": 0.0,
        "a_vencer_de_1801_ate_5400_dias": 0.0,
        "a_vencer_acima_de_5400_dias": 0.0,
        "risk_percent": 62.02,
        "risk_status": "Médio"
    }
]